fds/__init__.py
fds/sdk/__init__.py
fds/sdk/FactSetPrices/__init__.py
fds/sdk/FactSetPrices/api_client.py
fds/sdk/FactSetPrices/configuration.py
fds/sdk/FactSetPrices/exceptions.py
fds/sdk/FactSetPrices/model_utils.py
fds/sdk/FactSetPrices/rest.py
fds/sdk/FactSetPrices/api/__init__.py
fds/sdk/FactSetPrices/api/batch_processing_api.py
fds/sdk/FactSetPrices/api/database_rollover_api.py
fds/sdk/FactSetPrices/api/dividends_api.py
fds/sdk/FactSetPrices/api/high_low_api.py
fds/sdk/FactSetPrices/api/market_value_api.py
fds/sdk/FactSetPrices/api/prices_api.py
fds/sdk/FactSetPrices/api/reference_api.py
fds/sdk/FactSetPrices/api/returns_api.py
fds/sdk/FactSetPrices/api/shares_api.py
fds/sdk/FactSetPrices/api/splits_api.py
fds/sdk/FactSetPrices/apis/__init__.py
fds/sdk/FactSetPrices/model/__init__.py
fds/sdk/FactSetPrices/model/adjust.py
fds/sdk/FactSetPrices/model/batch.py
fds/sdk/FactSetPrices/model/batch_data_request.py
fds/sdk/FactSetPrices/model/batch_data_response.py
fds/sdk/FactSetPrices/model/batch_status.py
fds/sdk/FactSetPrices/model/batch_status_request.py
fds/sdk/FactSetPrices/model/batch_status_response.py
fds/sdk/FactSetPrices/model/calendar.py
fds/sdk/FactSetPrices/model/dividend.py
fds/sdk/FactSetPrices/model/dividend_adjust.py
fds/sdk/FactSetPrices/model/dividend_adjust_snapshot.py
fds/sdk/FactSetPrices/model/dividends_request.py
fds/sdk/FactSetPrices/model/dividends_response.py
fds/sdk/FactSetPrices/model/error_response.py
fds/sdk/FactSetPrices/model/error_response_sub_errors.py
fds/sdk/FactSetPrices/model/fixed_ids.py
fds/sdk/FactSetPrices/model/fixed_income_price.py
fds/sdk/FactSetPrices/model/frequency.py
fds/sdk/FactSetPrices/model/frequency_fi.py
fds/sdk/FactSetPrices/model/high_low.py
fds/sdk/FactSetPrices/model/high_low_request.py
fds/sdk/FactSetPrices/model/high_low_response.py
fds/sdk/FactSetPrices/model/ids_batch_max5000.py
fds/sdk/FactSetPrices/model/ids_max1000.py
fds/sdk/FactSetPrices/model/ids_max2000.py
fds.sdk.FactSetPrices-1.1.14.dist-info/LICENSE
fds.sdk.FactSetPrices-1.1.14.dist-info/METADATA
fds.sdk.FactSetPrices-1.1.14.dist-info/WHEEL
fds.sdk.FactSetPrices-1.1.14.dist-info/top_level.txt
fds.sdk.FactSetPrices-1.1.14.dist-info/RECORD
